redplanet/__init__.py
redplanet/utils.py
redplanet/Crust/Crust.py
redplanet/Crust/__init__.py
redplanet/GRS/GRS.py
redplanet/GRS/__init__.py
redplanet-1.0.0.dist-info/LICENSE.txt
redplanet-1.0.0.dist-info/METADATA
redplanet-1.0.0.dist-info/WHEEL
redplanet-1.0.0.dist-info/top_level.txt
redplanet-1.0.0.dist-info/RECORD
