Metadata-Version: 2.1
Name: redplanet
Version: 1.0.0
Summary: User-friendly access (i.e. APIs) for various Mars datasets and derived geophysics quantities. Create publication-ready plots on the fly or access the underlying data for more involved calculations.
Author-email: Zain Eris Kamal <zain.eris.kamal@rutgers.edu>
License: GNU GENERAL PUBLIC LICENSE
Project-URL: Homepage, https://github.com/Humboldt-Penguin/redplanet
Project-URL: Author, https://github.com/Humboldt-Penguin
Keywords: mars,geophysics,grs,crust,heat flow
Classifier: Development Status :: 5 - Production/Stable
Classifier: Operating System :: OS Independent
Classifier: Programming Language :: Python :: 3
Classifier: Programming Language :: Python :: 3 :: Only
Classifier: Intended Audience :: Developers
Classifier: Intended Audience :: Science/Research
Classifier: Topic :: Scientific/Engineering
Classifier: Topic :: Scientific/Engineering :: Physics
Classifier: Topic :: Scientific/Engineering :: GIS
Classifier: Natural Language :: English
Classifier: License :: OSI Approved :: GNU General Public License v3 (GPLv3)
Requires-Python: >=3.7
License-File: LICENSE.txt
Requires-Dist: pooch
Requires-Dist: gdown
Requires-Dist: pyshtools
Requires-Dist: numpy
Requires-Dist: matplotlib
Provides-Extra: jupyter
Requires-Dist: jupyter ; extra == 'jupyter'
Provides-Extra: jupyterlab
Requires-Dist: jupyterlab ; extra == 'jupyterlab'
